htmltopdfy/__init__.py
htmltopdfy/job.py
htmltopdfy-1.0.1.dist-info/LICENCE
htmltopdfy-1.0.1.dist-info/METADATA
htmltopdfy-1.0.1.dist-info/WHEEL
htmltopdfy-1.0.1.dist-info/top_level.txt
htmltopdfy-1.0.1.dist-info/RECORD
