Metadata-Version: 2.1
Name: htmltopdfy
Version: 1.0.1
Summary: Convert template html to pdf
Home-page: https://github.com/VolkenoMakers/htmlToPdf
Author: VOLKENO
Author-email: contact@volkeno-tank.com
License: MIT
Keywords: core package
Platform: UNKNOWN
Classifier: Development Status :: 5 - Production/Stable
Classifier: License :: OSI Approved :: MIT License
Classifier: Programming Language :: Python :: 3
Classifier: Operating System :: OS Independent
Classifier: Intended Audience :: Developers
License-File: LICENCE
Requires-Dist: htmltopdfy
